LICENSE
MANIFEST.in
README.rst
setup.cfg
setup.py
cryptocoins/__init__.py
cryptocoins/admin.py
cryptocoins/apps.py
cryptocoins/functions_nomodels.py
cryptocoins/models.py
cryptocoins/tests.py
cryptocoins/urls.py
cryptocoins/views.py
cryptocoins/management/__init__.py
cryptocoins/management/commands/J1_Update_Coins.py
cryptocoins/management/commands/__init__.py
cryptocoins/migrations/0001_initial.py
cryptocoins/migrations/0002_auto_20170708_2047.py
cryptocoins/migrations/0003_address.py
cryptocoins/migrations/0004_auto_20171028_1852.py
cryptocoins/migrations/0005_address_public_address.py
cryptocoins/migrations/0006_transaction.py
cryptocoins/migrations/0007_auto_20171029_1352.py
cryptocoins/migrations/0008_auto_20171030_2007.py
cryptocoins/migrations/__init__.py
django_cryptocoins.egg-info/PKG-INFO
django_cryptocoins.egg-info/SOURCES.txt
django_cryptocoins.egg-info/dependency_links.txt
django_cryptocoins.egg-info/top_level.txt